{
  "users": [
    {
      "firstName": "John",
      "lastName": "Doe",
      "email": "john.doe@example.com",
      "password": "password123",
      "phoneNumber": "1234567890"
    },
    {
      "firstName": "amer",
      "lastName": "Abu Zitouni",
      "email": "4mer.c56@gmail.com",
      "password": "sadsafsa",
      "phoneNumber": "56604310",
      "id": 2
    },
    {
      "firstName": "amer",
      "lastName": "Doe",
      "email": "john.doe@example.com",
      "password": "password123",
      "phoneNumber": "1234567890",
      "id": 3
    },
    {
      "firstName": "safs",
      "lastName": "saf",
      "email": "Am@gmail.com",
      "password": "safsaf",
      "phoneNumber": "5454",
      "id": 4
    },
    {
      "firstName": "asfdas",
      "lastName": "asfdsa",
      "email": "4mer.c56@gmail.com",
      "password": "aaaaaaa",
      "phoneNumber": "56604310",
      "id": 5
    }
  ],
  "product": [
    {
      "id": 1,
      "name": "بلوزة ولادي",
      "price": 30,
      "quantity": 1,
      "image": "https://cdn.salla.sa/zjDx/1hoxdAGYStSp9BCyqXWP2vcLRkyPzBzN5nGaJ5ad.jpg"
    },
    {
      "id": 2,
      "name": "حذاء رجالي",
      "price": 70,
      "quantity": 1,
      "image": "https://png.pngtree.com/png-vector/20201129/ourmid/pngtree-black-sneakers-png-image_2442993.jpg"
    },
    {
      "id": 3,
      "name": "حذاء رجالي",
      "price": 70,
      "quantity": 1,
      "image": "https://png.pngtree.com/png-vector/20201129/ourmid/pngtree-black-sneakers-png-image_2442993.jpg"
    }
  ],
  "list": [
    {
      "id": 1,
      "name": " بلوزة",
      "image": "https://sc01.alicdn.com/kf/HTB1g6tgayfrK1RjSspbq6A4pFXau/NS4115-Latest-New-Fashion-Women-Casual-White.jpg",
      "description": "بلوز قطن",
      "price": "50 شيكل"
    },
    {
      "id": 2,
      "name": " بلوزة",
      "image": "https://encrypted-tbn0.gstatic.com/images?q=tbn:ANd9GcT8cokejkGhpiQlomaf1F8vsNsoMFYpbfUz4w&s",
      "description": " بلوزة قطن  ",
      "price": "50 شيكل"
    },
    {
      "id": 1,
      "name": " حذاء",
      "image": "https://sc02.alicdn.com/kf/HTB1PqBtdwfH8KJjy1zcq6ATzpXa6/up-0372r-new-model-white-canvas-shoes.jpg",
      "description": "حذاء رجالي",
      "price": "50 شيكل"
    },
    {
      "id": 1,
      "name": " حذاء",
      "image": "https://sc02.alicdn.com/kf/HTB1PqBtdwfH8KJjy1zcq6ATzpXa6/up-0372r-new-model-white-canvas-shoes.jpg",
      "description": "حذاء رجالي",
      "price": "50 شيكل"
    },
    {
      "id": 1,
      "name": " حذاء",
      "image": "https://sc02.alicdn.com/kf/HTB1PqBtdwfH8KJjy1zcq6ATzpXa6/up-0372r-new-model-white-canvas-shoes.jpg",
      "description": "حذاء رجالي",
      "price": "50 شيكل"
    },
    {
      "id": 1,
      "name": " حذاء",
      "image": "https://sc02.alicdn.com/kf/HTB1PqBtdwfH8KJjy1zcq6ATzpXa6/up-0372r-new-model-white-canvas-shoes.jpg",
      "description": "حذاء رجالي",
      "price": "50 شيكل"
    },
    {
      "id": 1,
      "name": " حذاء",
      "image": "https://sc02.alicdn.com/kf/HTB1PqBtdwfH8KJjy1zcq6ATzpXa6/up-0372r-new-model-white-canvas-shoes.jpg",
      "description": "حذاء رجالي",
      "price": "50 شيكل"
    }
  ],
  "categories": [
    {
      "id": 1,
      "name": "Electronics",
      "slug": "electronics",
      "description": "Gadgets and devices",
      "image_url": "/images/categories/electronics.jpg"
    },
    {
      "id": 2,
      "name": "Fashion",
      "slug": "fashion",
      "description": "Clothing and accessories",
      "image_url": "/images/categories/fashion.jpg"
    },
    {
      "id": 3,
      "name": "Home & Kitchen",
      "slug": "home-kitchen",
      "description": "Furniture, appliances, and more",
      "image_url": "/images/categories/home-kitchen.jpg"
    },
    {
      "id": 4,
      "name": "Books",
      "slug": "books",
      "description": "Books, magazines, and e-books",
      "image_url": "/images/categories/books.jpg"
    }
  ],
  "products": [
    {
      "id": 101,
      "name": "Smartphone",
      "category_id": 1,
      "price": 699.99,
      "description": "Latest model smartphone with all new features.",
      "image_url": "/images/products/smartphone.jpg",
      "stock": 50
    },
    {
      "id": 102,
      "name": "Laptop",
      "category_id": 1,
      "price": 1099.99,
      "description": "High-performance laptop for professionals.",
      "image_url": "/images/products/laptop.jpg",
      "stock": 30
    },
    {
      "id": 201,
      "name": "Men's Jacket",
      "category_id": 2,
      "price": 99.99,
      "description": "Stylish men's jacket for winter.",
      "image_url": "/images/products/mens-jacket.jpg",
      "stock": 100
    }
  ]
}